fastfuzzysearch/__init__.py
fastfuzzysearch/fastfuzzysearch.py
fastfuzzysearch-0.0.10.dist-info/LICENSE
fastfuzzysearch-0.0.10.dist-info/METADATA
fastfuzzysearch-0.0.10.dist-info/WHEEL
fastfuzzysearch-0.0.10.dist-info/top_level.txt
fastfuzzysearch-0.0.10.dist-info/RECORD
