Metadata-Version: 2.1
Name: fastfuzzysearch
Version: 0.0.10
Summary: a Python package for fast fuzzy search entirely in-memory based
Home-page: https://github.com/eyalsus/fastfuzzysearch
Author: Eyal Paz
Author-email: eyalsus@gmail.com
License: BSD-3-Clause and Public-Domain
Keywords: search,fastsearch,fuzzy search,ngrams,aho-corasick,fastfuzzysearch,fuzzy
Platform: Linux
Platform: MacOSX
Platform: Windows
Classifier: Development Status :: 3 - Alpha
Classifier: Intended Audience :: Developers
Classifier: Topic :: Software Development :: Build Tools
Classifier: License :: OSI Approved :: BSD License
Classifier: Programming Language :: Python :: 3
Classifier: Programming Language :: Python :: 3.6
Classifier: Programming Language :: Python :: 3.7
Classifier: Programming Language :: Python :: 3.8
Requires-Dist: fastsearch
Requires-Dist: pyssdeep
Requires-Dist: six
Requires-Dist: numpy
Requires-Dist: pandas
Requires-Dist: dask
